django_sass/__init__.py
django_sass/apps.py
django_sass/management/commands/sass.py
django_sass-1.1.0.dist-info/LICENSE
django_sass-1.1.0.dist-info/METADATA
django_sass-1.1.0.dist-info/WHEEL
django_sass-1.1.0.dist-info/top_level.txt
django_sass-1.1.0.dist-info/RECORD
