Metadata-Version: 2.1
Name: django-sass
Version: 1.1.0
Summary: The absolute simplest way to use Sass with Django. Pure Python, minimal dependencies, and no special configuration required!
Home-page: https://github.com/coderedcorp/django-sass
Author: CodeRed LLC
Author-email: info@coderedcorp.com
License: BSD license
Platform: UNKNOWN
Classifier: Environment :: Web Environment
Classifier: Framework :: Django :: 2.0
Classifier: Framework :: Django :: 2.1
Classifier: Framework :: Django :: 2.2
Classifier: Framework :: Django :: 3.0
Classifier: Framework :: Django :: 3.1
Classifier: Framework :: Django
Classifier: Intended Audience :: Developers
Classifier: License :: OSI Approved :: BSD License
Classifier: Natural Language :: English
Classifier: Programming Language :: Python :: 3 :: Only
Classifier: Programming Language :: Python :: 3
Classifier: Programming Language :: Python :: 3.6
Classifier: Programming Language :: Python :: 3.7
Classifier: Programming Language :: Python :: 3.8
Classifier: Programming Language :: Python :: 3.9
